msql/__init__.py
msql/connection.py
msql/cursor.py
msql/database.py
msql/migration_tool.py
msql/py.typed
msql-1.2.1.dist-info/METADATA
msql-1.2.1.dist-info/WHEEL
msql-1.2.1.dist-info/top_level.txt
msql-1.2.1.dist-info/RECORD
