Metadata-Version: 2.1
Name: msql
Version: 1.2.1
Summary: Simple DSL with automatic migrations.
Home-page: UNKNOWN
Author: CERT Polska
Author-email: info@cert.pl
License: GPLv3
Platform: UNKNOWN
Classifier: Programming Language :: Python
Requires-Dist: mypy (==0.770)
Requires-Dist: mypy-extensions (==0.4.3)
Requires-Dist: typed-ast (==1.4.1)
Requires-Dist: typing-extensions (==3.7.4.1)
Provides-Extra: postgresql
Requires-Dist: psycopg2-binary (==2.7.3.2) ; extra == 'postgresql'
